lomo_mcp_demo/__init__.py
lomo_mcp_demo-0.1.0.dist-info/METADATA
lomo_mcp_demo-0.1.0.dist-info/WHEEL
lomo_mcp_demo-0.1.0.dist-info/entry_points.txt
lomo_mcp_demo-0.1.0.dist-info/RECORD
