Metadata-Version: 2.4
Name: lomo-mcp-demo
Version: 0.1.0
Summary: Add your description here
Author-email: Lomo <153917490@qq.com>
Requires-Python: >=3.12
Requires-Dist: mcp[cli]>=1.9.3
